django_react_cli/__init__.py
django_react_cli/__main__.py
django_react_cli/cli.py
django_react_cli-1.0.0.dist-info/licenses/LICENSE
django_react_cli-1.0.0.dist-info/METADATA
django_react_cli-1.0.0.dist-info/WHEEL
django_react_cli-1.0.0.dist-info/entry_points.txt
django_react_cli-1.0.0.dist-info/top_level.txt
django_react_cli-1.0.0.dist-info/RECORD
