Metadata-Version: 2.4
Name: django-react-cli
Version: 1.0.0
Summary: A starter template for building full-stack web applications using Django (backend), React (frontend), and TailwindCSS. Comes pre-configured with REST API support, authentication, and ready-to-use development and production settings.
Home-page: https://github.com
Author: code530pro
Author-email: hugo39452@gmail.com
Classifier: Programming Language :: Python :: 3
Classifier: License :: OSI Approved :: MIT License
Classifier: Operating System :: OS Independent
Requires-Python: >=3.7
License-File: LICENSE
Dynamic: author
Dynamic: author-email
Dynamic: classifier
Dynamic: description
Dynamic: description-content-type
Dynamic: home-page
Dynamic: license-file
Dynamic: requires-python
Dynamic: summary
